odop/__init__.py
odop/common.py
odop/odop_obs.py
odop/simulation.py
odop/task_definition.py
odop/cli/__init__.py
odop/cli/__main__.py
odop/cli/visualization/common.py
odop/cli/visualization/visualize_all_folder.py
odop/engine/cgroup.py
odop/engine/engine.py
odop/engine/execute_task.py
odop/scanner/__init__.py
odop/scanner/odop_scanner.py
odop/scanner/task_scanner.py
odop/scheduler/__init__.py
odop/scheduler/api.py
odop/scheduler/controller.py
odop/scheduler/scheduler_task.py
odop/scheduler/task_manager.py
odop/scheduler/task_queue.py
odop/scheduler/algorithms/__init__.py
odop/scheduler/algorithms/algorithm.py
odop/scheduler/algorithms/best_fit.py
odop/scheduler/algorithms/fifo.py
odop/scheduler/algorithms/priority.py
odop/scheduler/algorithms/round_robin.py
odop/ui/__init__.py
odop/ui/config.py
odop/ui/status.py
odop/ui/ui.py
odop/utils/README.md
odop/utils/__init__.py
odop/utils/dashboard.py
odop/utils/pages/current_optask.py
odop/utils/pages/real_time_monitoring.py
odop-0.0.1.dist-info/METADATA
odop-0.0.1.dist-info/WHEEL
odop-0.0.1.dist-info/entry_points.txt
odop-0.0.1.dist-info/licenses/LICENSE
odop-0.0.1.dist-info/RECORD
