Metadata-Version: 2.3
Name: odop
Version: 0.0.1
Summary: ODOP Engine in HPC
Project-URL: Repository, https://github.com/rdsea/odop
Project-URL: AaltoSEA, https://rdsea.github.io/
Author-email: AaltoSEA <linh.truong@aalto.fi>, nguu0123 <nguu0123@gmail.com>, rantahar <jarno.rantaharju@aalto.fi>, minhtribk12 <tri.m.nguyen@aalto.fi>
License: Apache-2.0
Requires-Python: >=3.6
Requires-Dist: click
Requires-Dist: cloudpickle
Requires-Dist: fastapi
Requires-Dist: loguru>=0.7.2
Requires-Dist: matplotlib
Requires-Dist: pydantic-settings
Requires-Dist: qoa4ml==0.3.18
Requires-Dist: streamlit>=1.39.0
Provides-Extra: dev
Requires-Dist: mypy; extra == 'dev'
Requires-Dist: pytest; extra == 'dev'
Provides-Extra: docs
Requires-Dist: myst-parser; extra == 'docs'
Requires-Dist: sphinx; extra == 'docs'
Requires-Dist: sphinx-rtd-theme; extra == 'docs'
